mindpile/__init__.py
mindpile/main.py
mindpile/IntermediateFormat/__init__.py
mindpile/IntermediateFormat/objects.py
mindpile/Mapping/__init__.py
mindpile/Mapping/boilerplate.py
mindpile/Mapping/control.py
mindpile/Mapping/types.py
mindpile/Mapping/utils.py
mindpile/Mapping/actions/display.py
mindpile/Mapping/actions/largeMotor.py
mindpile/Mapping/actions/light.py
mindpile/Mapping/actions/mediumMotor.py
mindpile/Mapping/actions/sound.py
mindpile/Mapping/actions/steering.py
mindpile/Mapping/actions/tank.py
mindpile/Mapping/advanced/comment.py
mindpile/Mapping/data/__init__.py
mindpile/Mapping/data/array.py
mindpile/Mapping/data/compare.py
mindpile/Mapping/data/constants.py
mindpile/Mapping/data/logic.py
mindpile/Mapping/data/maths.py
mindpile/Mapping/data/random.py
mindpile/Mapping/data/range.py
mindpile/Mapping/data/round.py
mindpile/Mapping/data/text.py
mindpile/Mapping/data/variables.py
mindpile/Mapping/ev3sim/__init__.py
mindpile/Mapping/sensors/__init__.py
mindpile/Mapping/sensors/brick.py
mindpile/Mapping/sensors/colour.py
mindpile/Mapping/sensors/ir.py
mindpile/Mapping/sensors/motor.py
mindpile/Parser/__init__.py
mindpile/Parser/tagHandler.py
mindpile/Utility/__init__.py
mindpile/Utility/exceptions.py
mindpile/Utility/memo.py
mindpile/Utility/types.py
mindpile/Utility/utility.py
mindpile-0.0.2.dist-info/LICENSE
mindpile-0.0.2.dist-info/METADATA
mindpile-0.0.2.dist-info/WHEEL
mindpile-0.0.2.dist-info/entry_points.txt
mindpile-0.0.2.dist-info/top_level.txt
mindpile-0.0.2.dist-info/RECORD
