Metadata-Version: 2.1
Name: mindpile
Version: 0.0.2
Summary: Transpiles Mindstorms to ev3dev2 python.
Home-page: https://github.com/MelbourneHighSchoolRobotics/mindpile
Author: Angus Trau, Richard Huang, Jackson Goerner, Peter Drew
Author-email: contact@angus.ws, me@huangrichard.com, jgoerner@outlook.com, peter@pdrew.com
License: BSD-3-Clause
Platform: UNKNOWN
Classifier: License :: OSI Approved :: BSD License
Classifier: Programming Language :: Python
Classifier: Programming Language :: Python :: 3
Requires-Python: >=3.9.0
